lms_hikvision/__init__.py
lms_hikvision/admin.py
lms_hikvision/apps.py
lms_hikvision/models.py
lms_hikvision/serializers.py
lms_hikvision/tests.py
lms_hikvision/urls.py
lms_hikvision/utils.py
lms_hikvision/views.py
lms_hikvision/migrations/__init__.py
lms_hikvision/static/lms_hikvision/css/lib/element-plus.css
lms_hikvision/static/lms_hikvision/js/lib/h5player.min.js
lms_hikvision/static/lms_hikvision/js/lib/echarts/echarts.min.js
lms_hikvision/static/lms_hikvision/js/lib/element/dayjs.min.js
lms_hikvision/static/lms_hikvision/js/lib/element/element-plus.min.js
lms_hikvision/static/lms_hikvision/js/lib/element/zh-cn.js
lms_hikvision/static/lms_hikvision/js/lib/playctrl1/DecodeWorker.js
lms_hikvision/static/lms_hikvision/js/lib/playctrl1/Decoder.js
lms_hikvision/static/lms_hikvision/js/lib/vue/vue.global.prod.js
lms_hikvision/templates/common.html
lms_hikvision/templates/lms_hikvision/history.html
lms_hikvision/templates/lms_hikvision/playback.html
lms_hikvision/templates/lms_hikvision/preview.html
lms_hikvision/templates/lms_hikvision/tvwall.html
lms_hikvision-0.4.0.dist-info/licenses/LICENSE
lms_hikvision-0.4.0.dist-info/METADATA
lms_hikvision-0.4.0.dist-info/WHEEL
lms_hikvision-0.4.0.dist-info/top_level.txt
lms_hikvision-0.4.0.dist-info/RECORD
